dailysignin/__init__.py
dailysignin/__version__.py
dailysignin/configs.py
dailysignin/main.py
dailysignin/acfun/__init__.py
dailysignin/acfun/main.py
dailysignin/aliyun/__init__.py
dailysignin/aliyun/main.py
dailysignin/aolaxing/__init__.py
dailysignin/aolaxing/main.py
dailysignin/baidu/__init__.py
dailysignin/baidu/main.py
dailysignin/bilibili/__init__.py
dailysignin/bilibili/main.py
dailysignin/enshan/__init__.py
dailysignin/enshan/main.py
dailysignin/fnos/__init__.py
dailysignin/fnos/main.py
dailysignin/imaotai/__init__.py
dailysignin/imaotai/main.py
dailysignin/iqiyi/__init__.py
dailysignin/iqiyi/main.py
dailysignin/kgqq/__init__.py
dailysignin/kgqq/main.py
dailysignin/mimotion/__init__.py
dailysignin/mimotion/main.py
dailysignin/smzdm/__init__.py
dailysignin/smzdm/main.py
dailysignin/tieba/__init__.py
dailysignin/tieba/main.py
dailysignin/utils/__init__.py
dailysignin/utils/message.py
dailysignin/v2ex/__init__.py
dailysignin/v2ex/main.py
dailysignin/youdao/__init__.py
dailysignin/youdao/main.py
dailysignin-25.1.8.dist-info/LICENSE
dailysignin-25.1.8.dist-info/METADATA
dailysignin-25.1.8.dist-info/WHEEL
dailysignin-25.1.8.dist-info/entry_points.txt
dailysignin-25.1.8.dist-info/top_level.txt
dailysignin-25.1.8.dist-info/RECORD
