Metadata-Version: 2.2
Name: dailysignin
Version: 25.1.8
Summary: dailysignin
Home-page: https://pipimao.cn
Author: MengMei
Author-email: wangziqi0702@vip.qq.com
License: MIT
Project-URL: Documentation, https://tina0597.github.io/dailysignin/
Classifier: License :: OSI Approved :: MIT License
Classifier: Programming Language :: Python :: 3.9
Classifier: Programming Language :: Python :: 3.10
Classifier: Programming Language :: Python :: Implementation :: CPython
Classifier: Programming Language :: Python :: Implementation :: PyPy
Requires-Python: >=3.9.0
License-File: LICENSE
Requires-Dist: pycryptodome==3.17
Requires-Dist: requests~=2.25.1
Requires-Dist: rsa~=4.0
Requires-Dist: urllib3~=1.26.2
Dynamic: author
Dynamic: author-email
Dynamic: classifier
Dynamic: description
Dynamic: description-content-type
Dynamic: home-page
Dynamic: license
Dynamic: project-url
Dynamic: requires-dist
Dynamic: requires-python
Dynamic: summary
